<?xml version="1.0"?>
<!DOCTYPE hibernate-mapping PUBLIC "-//Hibernate/Hibernate Mapping DTD 3.0//EN"
"http://www.hibernate.org/dtd/hibernate-mapping-3.0.dtd">
<!-- Generated 26/11/2021 13:09:36 by Hibernate Tools 4.3.1 -->
<hibernate-mapping>
    <class name="modelo.Servicio" table="servicio" schema="public" optimistic-lock="version">
        <id name="id" type="long">
            <column name="id" />
            <generator class="assigned" />
        </id>
        <property name="tiposervicio" type="string">
            <column name="tiposervicio" length="20" />
        </property>
        <property name="monto" type="java.lang.Double">
            <column name="monto" precision="17" scale="17" />
        </property>
    </class>
</hibernate-mapping>
